pinecone/__init__.py
pinecone/__version__
pinecone/config/__init__.py
pinecone/config/config.py
pinecone/config/openapi.py
pinecone/config/pinecone_config.py
pinecone/control/__init__.py
pinecone/control/index_host_store.py
pinecone/control/pinecone.py
pinecone/core/__init__.py
pinecone/core/client/__init__.py
pinecone/core/client/api/__init__.py
pinecone/core/client/api/data_plane_api.py
pinecone/core/client/api/manage_indexes_api.py
pinecone/core/client/api_client.py
pinecone/core/client/apis/__init__.py
pinecone/core/client/configuration.py
pinecone/core/client/exceptions.py
pinecone/core/client/model/__init__.py
pinecone/core/client/model/collection_list.py
pinecone/core/client/model/collection_model.py
pinecone/core/client/model/configure_index_request.py
pinecone/core/client/model/configure_index_request_spec.py
pinecone/core/client/model/configure_index_request_spec_pod.py
pinecone/core/client/model/create_collection_request.py
pinecone/core/client/model/create_index_request.py
pinecone/core/client/model/delete_request.py
pinecone/core/client/model/describe_index_stats_request.py
pinecone/core/client/model/describe_index_stats_response.py
pinecone/core/client/model/error_response.py
pinecone/core/client/model/error_response_error.py
pinecone/core/client/model/fetch_response.py
pinecone/core/client/model/index_list.py
pinecone/core/client/model/index_model.py
pinecone/core/client/model/index_model_spec.py
pinecone/core/client/model/index_model_status.py
pinecone/core/client/model/list_item.py
pinecone/core/client/model/list_response.py
pinecone/core/client/model/namespace_summary.py
pinecone/core/client/model/pagination.py
pinecone/core/client/model/pod_spec.py
pinecone/core/client/model/pod_spec_metadata_config.py
pinecone/core/client/model/protobuf_any.py
pinecone/core/client/model/protobuf_null_value.py
pinecone/core/client/model/query_request.py
pinecone/core/client/model/query_response.py
pinecone/core/client/model/query_vector.py
pinecone_client-3.2.1.dist-info/LICENSE.txt
pinecone_client-3.2.1.dist-info/METADATA
pinecone_client-3.2.1.dist-info/WHEEL
pinecone_client-3.2.1.dist-info/RECORD
